mcp_doc_scraper/__init__.py
mcp_doc_scraper/__main__.py
mcp_doc_scraper/server.py
mseep_mcp_doc_scraper-0.1.4.dist-info/METADATA
mseep_mcp_doc_scraper-0.1.4.dist-info/WHEEL
mseep_mcp_doc_scraper-0.1.4.dist-info/entry_points.txt
mseep_mcp_doc_scraper-0.1.4.dist-info/top_level.txt
mseep_mcp_doc_scraper-0.1.4.dist-info/RECORD
