Metadata-Version: 2.4
Name: mseep-mcp_doc_scraper
Version: 0.1.4
Summary: MCP server for scraping documentation
Author-email: mseep <support@skydeck.ai>
Requires-Python: >=3.7
Requires-Dist: aiohttp
Requires-Dist: mcp
Requires-Dist: pydantic
